ssoproject/__init__.py
ssoproject/asgi.py
ssoproject/settings.py
ssoproject/urls.py
ssoproject/wsgi.py
users/__init__.py
users/admin.py
users/apps.py
users/consts.py
users/models.py
users/tests.py
users/urls.py
users/views.py
users/migrations/__init__.py
singlesignondemotest-0.6.dist-info/METADATA
singlesignondemotest-0.6.dist-info/WHEEL
singlesignondemotest-0.6.dist-info/top_level.txt
singlesignondemotest-0.6.dist-info/RECORD
